{
  "main": {
    "id": "00db1271106040b1",
    "type": "split",
    "children": [
      {
        "id": "44e3b3ec60386652",
        "type": "tabs",
        "children": [
          {
            "id": "0132fda8fe7d6c2e",
            "type": "leaf",
            "state": {
              "type": "empty",
              "state": {},
              "icon": "lucide-file",
              "title": "새 탭"
            }
          }
        ]
      }
    ],
    "direction": "vertical"
  },
  "left": {
    "id": "41865801e4ef1a9a",
    "type": "split",
    "children": [
      {
        "id": "ab2091b2e38fc353",
        "type": "tabs",
        "children": [
          {
            "id": "fc0d0ed5137ae747",
            "type": "leaf",
            "state": {
              "type": "file-explorer",
              "state": {
                "sortOrder": "alphabetical",
                "autoReveal": false
              },
              "icon": "lucide-folder-closed",
              "title": "파일 탐색기"
            }
          },
          {
            "id": "c34d959aa56bcc87",
            "type": "leaf",
            "state": {
              "type": "search",
              "state": {
                "query": "",
                "matchingCase": false,
                "explainSearch": false,
                "collapseAll": false,
                "extraContext": false,
                "sortOrder": "alphabetical"
              },
              "icon": "lucide-search",
              "title": "검색"
            }
          },
          {
            "id": "7b09bd4b65226ee5",
            "type": "leaf",
            "state": {
              "type": "bookmarks",
              "state": {},
              "icon": "lucide-bookmark",
              "title": "북마크"
            }
          }
        ]
      }
    ],
    "direction": "horizontal",
    "width": 300
  },
  "right": {
    "id": "73390c91c79638a8",
    "type": "split",
    "children": [
      {
        "id": "a82aefceff566565",
        "type": "tabs",
        "children": [
          {
            "id": "cd4863480a67f7e9",
            "type": "leaf",
            "state": {
              "type": "backlink",
              "state": {
                "collapseAll": false,
                "extraContext": false,
                "sortOrder": "alphabetical",
                "showSearch": false,
                "searchQuery": "",
                "backlinkCollapsed": false,
                "unlinkedCollapsed": true
              },
              "icon": "links-coming-in",
              "title": "백링크"
            }
          },
          {
            "id": "f1593917131365f6",
            "type": "leaf",
            "state": {
              "type": "outgoing-link",
              "state": {
                "linksCollapsed": false,
                "unlinkedCollapsed": true
              },
              "icon": "links-going-out",
              "title": "나가는 링크"
            }
          },
          {
            "id": "a9c2bd5580ff2ebe",
            "type": "leaf",
            "state": {
              "type": "tag",
              "state": {
                "sortOrder": "frequency",
                "useHierarchy": true,
                "showSearch": false,
                "searchQuery": ""
              },
              "icon": "lucide-tags",
              "title": "태그"
            }
          },
          {
            "id": "f78c4e7e46764207",
            "type": "leaf",
            "state": {
              "type": "all-properties",
              "state": {
                "sortOrder": "frequency",
                "showSearch": false,
                "searchQuery": ""
              },
              "icon": "lucide-archive",
              "title": "모든 속성"
            }
          },
          {
            "id": "43198cd801137506",
            "type": "leaf",
            "state": {
              "type": "outline",
              "state": {
                "followCursor": false,
                "showSearch": false,
                "searchQuery": ""
              },
              "icon": "lucide-list",
              "title": "개요"
            }
          }
        ]
      }
    ],
    "direction": "horizontal",
    "width": 300,
    "collapsed": true
  },
  "left-ribbon": {
    "hiddenItems": {
      "switcher:빠른 전환기 열기": false,
      "graph:그래프 뷰 열기": false,
      "canvas:새 캔버스 만들기": false,
      "daily-notes:오늘의 일일 노트 열기": false,
      "templates:템플릿 삽입": false,
      "command-palette:명령어 팔레트 열기": false,
      "bases:새 베이스 생성하기": false
    }
  },
  "active": "0132fda8fe7d6c2e",
  "lastOpenFiles": []
}